prp1/__init__.py
prp1-1.0.4.dist-info/LICENSE.txt
prp1-1.0.4.dist-info/METADATA
prp1-1.0.4.dist-info/WHEEL
prp1-1.0.4.dist-info/top_level.txt
prp1-1.0.4.dist-info/RECORD
